mycloudhome/__init__.py
mycloudhome/auth.py
mycloudhome/configure.py
mycloudhome/device.py
mycloudhome/filemanagement.py
mycloudhome/main.py
mycloudhome/resumablefiles.py
mycloudhome/utils.py
mycloudhome-2022.2.22.dist-info/LICENSE
mycloudhome-2022.2.22.dist-info/METADATA
mycloudhome-2022.2.22.dist-info/WHEEL
mycloudhome-2022.2.22.dist-info/entry_points.txt
mycloudhome-2022.2.22.dist-info/top_level.txt
mycloudhome-2022.2.22.dist-info/RECORD
