Metadata-Version: 2.1
Name: mycloudhome
Version: 2022.2.22
Summary: mycloudhome - a CLI tool for wd mycloud home.
Home-page: UNKNOWN
Author: Yang Yu
Author-email: yang.lights@hotmail.com
License: MIT
Keywords: WD My Cloud Home,western digital,cli,file management
Platform: UNKNOWN
Requires-Python: >=3.6
Requires-Dist: requests
Requires-Dist: click
Requires-Dist: progress
